<?xml version="1.0" encoding="utf-8"?>
<edmx:Edmx Version="4.0" xmlns:edmx="http://docs.oasis-open.org/odata/ns/edmx">
    <edmx:Reference Uri="https://oasis-tcs.github.io/odata-vocabularies/vocabularies/Org.OData.Capabilities.V1.xml">
        <edmx:Include Alias="Capabilities" Namespace="Org.OData.Capabilities.V1"/>
    </edmx:Reference>
    <edmx:Reference Uri="https://sap.github.io/odata-vocabularies/vocabularies/Common.xml">
        <edmx:Include Alias="Common" Namespace="com.sap.vocabularies.Common.v1"/>
    </edmx:Reference>
    <edmx:Reference Uri="https://oasis-tcs.github.io/odata-vocabularies/vocabularies/Org.OData.Core.V1.xml">
        <edmx:Include Alias="Core" Namespace="Org.OData.Core.V1"/>
    </edmx:Reference>
    <edmx:Reference Uri="https://sap.github.io/odata-vocabularies/vocabularies/UI.xml">
        <edmx:Include Alias="UI" Namespace="com.sap.vocabularies.UI.v1"/>
    </edmx:Reference>
    <edmx:DataServices>
        <Schema Namespace="CatalogService" xmlns="http://docs.oasis-open.org/odata/ns/edm">
            <EntityContainer Name="EntityContainer">
                <EntitySet Name="Books" EntityType="CatalogService.Books">
                    <NavigationPropertyBinding Path="author" Target="Authors"/>
                </EntitySet>
                <EntitySet Name="Authors" EntityType="CatalogService.Authors">
                    <NavigationPropertyBinding Path="books" Target="Books"/>
                </EntitySet>
                <EntitySet Name="Orders" EntityType="CatalogService.Orders">
                    <NavigationPropertyBinding Path="book" Target="Books"/>
                </EntitySet>
            </EntityContainer>
            <EntityType Name="Books">
                <Key>
                    <PropertyRef Name="ID"/>
                </Key>
                <Property Name="ID" Type="Edm.Int32" Nullable="false"/>
                <Property Name="title" Type="Edm.String"/>
                <Property Name="stock" Type="Edm.Int32"/>
                <NavigationProperty Name="author" Type="CatalogService.Authors" Partner="books">
                    <ReferentialConstraint Property="author_ID" ReferencedProperty="ID"/>
                </NavigationProperty>
                <Property Name="author_ID" Type="Edm.Int32"/>
            </EntityType>
            <EntityType Name="Authors">
                <Key>
                    <PropertyRef Name="ID"/>
                </Key>
                <Property Name="ID" Type="Edm.Int32" Nullable="false"/>
                <Property Name="name" Type="Edm.String"/>
                <NavigationProperty Name="books" Type="Collection(CatalogService.Books)" Partner="author"/>
            </EntityType>
            <EntityType Name="Orders">
                <Key>
                    <PropertyRef Name="ID"/>
                </Key>
                <Property Name="ID" Type="Edm.Guid" Nullable="false"/>
                <Property Name="createdAt" Type="Edm.DateTimeOffset" Precision="7"/>
                <Property Name="createdBy" Type="Edm.String" MaxLength="255"/>
                <Property Name="modifiedAt" Type="Edm.DateTimeOffset" Precision="7"/>
                <Property Name="modifiedBy" Type="Edm.String" MaxLength="255"/>
                <NavigationProperty Name="book" Type="CatalogService.Books">
                    <ReferentialConstraint Property="book_ID" ReferencedProperty="ID"/>
                </NavigationProperty>
                <Property Name="book_ID" Type="Edm.Int32"/>
                <Property Name="quantity" Type="Edm.Int32"/>
            </EntityType>
            <Annotations Target="CatalogService.Books">
                <Annotation Term="UI.LineItem">
                    <Collection>
                        <Record Type="UI.DataField">
                            <PropertyValue Property="Value" Path="ID"/>
                            <PropertyValue Property="Label" String="Book ID"/>
                        </Record>
                        <Record Type="UI.DataField">
                            <PropertyValue Property="Value" Path="title"/>
                            <PropertyValue Property="Label" String="Title"/>
                        </Record>
                    </Collection>
                </Annotation>
                <Annotation Term="UI.HeaderInfo">
                    <Record Type="UI.HeaderInfoType">
                        <PropertyValue Property="Title">
                            <Record Type="UI.DataField">
                                <PropertyValue Property="Value" Path="ID"/>
                            </Record>
                        </PropertyValue>
                        <PropertyValue Property="Description">
                            <Record Type="UI.DataField">
                                <PropertyValue Property="Value" Path="title"/>
                            </Record>
                        </PropertyValue>
                    </Record>
                </Annotation>
            </Annotations>
            <Annotations Target="CatalogService.EntityContainer/Books">
                <Annotation Term="Capabilities.InsertRestrictions">
                    <Record Type="Capabilities.InsertRestrictionsType">
                        <PropertyValue Property="Insertable" Bool="true"/>
                    </Record>
                </Annotation>
                <Annotation Term="Capabilities.DeleteRestrictions">
                    <Record Type="Capabilities.DeleteRestrictionsType">
                        <PropertyValue Property="Deletable" Bool="true"/>
                    </Record>
                </Annotation>
                <Annotation Term="Capabilities.UpdateRestrictions">
                    <Record Type="Capabilities.UpdateRestrictionsType">
                        <PropertyValue Property="Updatable" Bool="true"/>
                    </Record>
                </Annotation>
            </Annotations>
            <Annotations Target="CatalogService.Authors">
                <Annotation Term="UI.LineItem">
                    <Collection>
                        <Record Type="UI.DataField">
                            <PropertyValue Property="Label" String="ID"/>
                            <PropertyValue Property="Value" Path="ID"/>
                        </Record>
                        <Record Type="UI.DataField">
                            <PropertyValue Property="Label" String="Name"/>
                            <PropertyValue Property="Value" Path="name"/>
                        </Record>
                    </Collection>
                </Annotation>
                <Annotation Term="UI.FieldGroup" Qualifier="GeneratedGroup2">
                    <Record Type="UI.FieldGroupType">
                        <PropertyValue Property="Data">
                            <Collection>
                                <Record Type="UI.DataField">
                                    <PropertyValue Property="Label" String="ID"/>
                                    <PropertyValue Property="Value" Path="ID"/>
                                </Record>
                                <Record Type="UI.DataField">
                                    <PropertyValue Property="Label" String="Name"/>
                                    <PropertyValue Property="Value" Path="name"/>
                                </Record>
                            </Collection>
                        </PropertyValue>
                    </Record>
                </Annotation>
                <Annotation Term="UI.Facets">
                    <Collection>
                        <Record Type="UI.ReferenceFacet">
                            <PropertyValue Property="ID" String="GeneratedFacet2"/>
                            <PropertyValue Property="Label" String="General Information"/>
                            <PropertyValue Property="Target" AnnotationPath="@UI.FieldGroup#GeneratedGroup2"/>
                        </Record>
                        <Record Type="UI.ReferenceFacet">
                            <PropertyValue Property="Label" String="Associated Books"/>
                            <PropertyValue Property="Target" AnnotationPath="books/@UI.LineItem"/>
                        </Record>
                    </Collection>
                </Annotation>
            </Annotations>
            <Annotations Target="CatalogService.EntityContainer/Authors">
                <Annotation Term="Capabilities.DeleteRestrictions">
                    <Record Type="Capabilities.DeleteRestrictionsType">
                        <PropertyValue Property="Deletable" Bool="false"/>
                    </Record>
                </Annotation>
                <Annotation Term="Capabilities.InsertRestrictions">
                    <Record Type="Capabilities.InsertRestrictionsType">
                        <PropertyValue Property="Insertable" Bool="false"/>
                    </Record>
                </Annotation>
                <Annotation Term="Capabilities.UpdateRestrictions">
                    <Record Type="Capabilities.UpdateRestrictionsType">
                        <PropertyValue Property="Updatable" Bool="false"/>
                    </Record>
                </Annotation>
            </Annotations>
            <Annotations Target="CatalogService.Orders/createdAt">
                <Annotation Term="UI.HiddenFilter" Bool="true"/>
                <Annotation Term="Core.Immutable" Bool="true"/>
                <Annotation Term="Core.Computed" Bool="true"/>
                <Annotation Term="Common.Label" String="{i18n>CreatedAt}"/>
                </Annotations>
                <Annotations Target="CatalogService.Orders/createdBy">
                    <Annotation Term="UI.HiddenFilter" Bool="true"/>
                    <Annotation Term="Core.Immutable" Bool="true"/>
                    <Annotation Term="Core.Computed" Bool="true"/>
                    <Annotation Term="Core.Description" String="{i18n>UserID.Description}"/>
                        <Annotation Term="Common.Label" String="{i18n>CreatedBy}"/>
                        </Annotations>
                        <Annotations Target="CatalogService.Orders/modifiedAt">
                            <Annotation Term="UI.HiddenFilter" Bool="true"/>
                            <Annotation Term="Core.Computed" Bool="true"/>
                            <Annotation Term="Common.Label" String="{i18n>ChangedAt}"/>
                            </Annotations>
                            <Annotations Target="CatalogService.Orders/modifiedBy">
                                <Annotation Term="UI.HiddenFilter" Bool="true"/>
                                <Annotation Term="Core.Computed" Bool="true"/>
                                <Annotation Term="Core.Description" String="{i18n>UserID.Description}"/>
                                    <Annotation Term="Common.Label" String="{i18n>ChangedBy}"/>
                                    </Annotations>
                                </Schema>
                            </edmx:DataServices>
                        </edmx:Edmx>